vtkwriters/__init__.py
vtkwriters/_version.py
vtkwriters/_vtkwriters.py
vtkwriters-0.0.12.dist-info/LICENSE
vtkwriters-0.0.12.dist-info/METADATA
vtkwriters-0.0.12.dist-info/WHEEL
vtkwriters-0.0.12.dist-info/top_level.txt
vtkwriters-0.0.12.dist-info/RECORD
