Metadata-Version: 2.1
Name: vtkwriters
Version: 0.0.12
Author-email: Simon Lopez <s.lopez@brgm.fr>
License: GPL version 3
Project-URL: url, https://gitlab.com/brgm/geomodelling/io/vtkwriters
Keywords: vtk,paraview
License-File: LICENSE
Requires-Dist: numpy
Requires-Dist: verstr
